backend_pool/README.md
backend_pool/__init__.py
backend_pool/nat.py
backend_pool/pool_server.py
backend_pool/pool_service.py
backend_pool/ssh_exec.py
backend_pool/telnet_exec.py
backend_pool/util.py
backend_pool/libvirt/__init__.py
backend_pool/libvirt/backend_service.py
backend_pool/libvirt/guest_handler.py
backend_pool/libvirt/network_handler.py
backend_pool/libvirt/snapshot_handler.py
cowrie/__init__.py
cowrie/_version.py
cowrie/commands/__init__.py
cowrie/commands/adduser.py
cowrie/commands/apt.py
cowrie/commands/awk.py
cowrie/commands/base.py
cowrie/commands/base64.py
cowrie/commands/bash.py
cowrie/commands/busybox.py
cowrie/commands/cat.py
cowrie/commands/chmod.py
cowrie/commands/chpasswd.py
cowrie/commands/crontab.py
cowrie/commands/curl.py
cowrie/commands/dd.py
cowrie/commands/dig.py
cowrie/commands/du.py
cowrie/commands/env.py
cowrie/commands/ethtool.py
cowrie/commands/find.py
cowrie/commands/finger.py
cowrie/commands/free.py
cowrie/commands/fs.py
cowrie/commands/ftpget.py
cowrie/commands/gcc.py
cowrie/commands/git.py
cowrie/commands/groups.py
cowrie/commands/ifconfig.py
cowrie/commands/iptables.py
cowrie/commands/last.py
cowrie/commands/locate.py
cowrie/commands/ls.py
cowrie/commands/lspci.py
cowrie/commands/nc.py
cowrie/commands/netstat.py
cowrie/commands/nohup.py
cowrie/commands/perl.py
cowrie/commands/ping.py
cowrie/commands/python.py
cowrie/commands/scp.py
cowrie/commands/service.py
cowrie/commands/sleep.py
cowrie/commands/ssh.py
cowrie/commands/sudo.py
cowrie/commands/tar.py
cowrie/commands/tee.py
cowrie/commands/tftp.py
cowrie/commands/ulimit.py
cowrie/commands/uname.py
cowrie/commands/uniq.py
cowrie/commands/unzip.py
cowrie/commands/uptime.py
cowrie/commands/wc.py
cowrie/commands/wget.py
cowrie/commands/which.py
cowrie/commands/yum.py
cowrie/core/__init__.py
cowrie/core/artifact.py
cowrie/core/auth.py
cowrie/core/cef.py
cowrie/core/checkers.py
cowrie/core/config.py
cowrie/core/credentials.py
cowrie/core/network.py
cowrie/core/output.py
cowrie-2.8.1.dist-info/licenses/LICENSE.rst
cowrie-2.8.1.dist-info/METADATA
cowrie-2.8.1.dist-info/WHEEL
cowrie-2.8.1.dist-info/entry_points.txt
cowrie-2.8.1.dist-info/top_level.txt
cowrie-2.8.1.dist-info/RECORD
