Metadata-Version: 2.4
Name: cowrie
Version: 2.8.1
Summary: Cowrie SSH/Telnet Honeypot.
Author-email: Michel Oosterhof <michel@oosterhof.net>
Maintainer-email: Michel Oosterhof <michel@oosterhof.net>
License-Expression: BSD-3-Clause
Project-URL: homepage, https://www.cowrie.org/
Project-URL: documentation, https://docs.cowrie.org/
Project-URL: repository, https://github.com/cowrie/cowrie
Keywords: ssh,telnet,honeypot
Classifier: Development Status :: 5 - Production/Stable
Classifier: Environment :: No Input/Output (Daemon)
Classifier: Framework :: Twisted
Classifier: Intended Audience :: Developers
Classifier: Intended Audience :: System Administrators
Classifier: Operating System :: MacOS :: MacOS X
Classifier: Operating System :: POSIX :: Linux
Classifier: Operating System :: POSIX
Classifier: Programming Language :: Python
Classifier: Programming Language :: Python :: 3
Classifier: Programming Language :: Python :: 3 :: Only
Classifier: Topic :: Security
Requires-Python: !=3.0.*,!=3.1.*,!=3.2.*,!=3.3.*,!=3.4.*,!=3.5.*,!=3.6.*,!=3.7.*,!=3.8.*,!=3.9.*,<4,>=2.7
License-File: LICENSE.rst
Requires-Dist: attrs==25.3.0
Requires-Dist: bcrypt==5.0.0
Requires-Dist: cryptography==46.0.1
Requires-Dist: hyperlink==21.0.0
Requires-Dist: idna==3.10
Requires-Dist: packaging==25.0
Requires-Dist: pyasn1_modules==0.4.2
Requires-Dist: requests==2.32.5
Requires-Dist: service_identity==24.2.0
Requires-Dist: tftpy==0.8.6
Requires-Dist: treq==25.5.0
Requires-Dist: twisted[conch]==25.5.0
Provides-Extra: csirtg
Requires-Dist: csirtgsdk==1.1.5; extra == "csirtg"
Provides-Extra: dshield
Requires-Dist: requests; extra == "dshield"
Provides-Extra: elasticsearch
Requires-Dist: pyes; extra == "elasticsearch"
Provides-Extra: mysql
Requires-Dist: mysqlclient; extra == "mysql"
Provides-Extra: mongodb
Requires-Dist: pymongo; extra == "mongodb"
Provides-Extra: pool
Requires-Dist: libvirt-python==11.8.0; extra == "pool"
Provides-Extra: rethinkdblog
Requires-Dist: rethinkdb; extra == "rethinkdblog"
Provides-Extra: s3
Requires-Dist: botocore; extra == "s3"
Provides-Extra: slack
Requires-Dist: slackclient; extra == "slack"
Provides-Extra: influxdb
Requires-Dist: influxdb; extra == "influxdb"
Provides-Extra: dev
Requires-Dist: build==1.3.0; extra == "dev"
Requires-Dist: coverage==7.10.6; extra == "dev"
Requires-Dist: mypy-extensions==1.1.0; platform_python_implementation == "CPython" and extra == "dev"
Requires-Dist: mypy-zope==1.0.13; platform_python_implementation == "CPython" and extra == "dev"
Requires-Dist: mypy==1.17.1; platform_python_implementation == "CPython" and extra == "dev"
Requires-Dist: pathspec==0.12.1; extra == "dev"
Requires-Dist: pipdeptree==2.28.0; extra == "dev"
Requires-Dist: pre-commit==4.3.0; extra == "dev"
Requires-Dist: pylint==3.3.8; extra == "dev"
Requires-Dist: pyre-check==0.9.25; extra == "dev"
Requires-Dist: pyright==1.1.405; extra == "dev"
Requires-Dist: pytype==2024.10.11; platform_python_implementation == "CPython" and extra == "dev"
Requires-Dist: pyupgrade==3.20.0; extra == "dev"
Requires-Dist: pyyaml==6.0.3; extra == "dev"
Requires-Dist: readthedocs-sphinx-search==0.3.2; extra == "dev"
Requires-Dist: ruff==0.13.3; extra == "dev"
Requires-Dist: setuptools==80.9.0; extra == "dev"
Requires-Dist: sphinx-copybutton==0.5.2; extra == "dev"
Requires-Dist: sphinx_rtd_theme==3.0.2; extra == "dev"
Requires-Dist: tox==4.30.2; extra == "dev"
Requires-Dist: types-python-dateutil==2.9.0.20250822; extra == "dev"
Requires-Dist: types-redis==4.6.0.20241004; extra == "dev"
Requires-Dist: types-requests==2.32.4.20250913; extra == "dev"
Requires-Dist: yamllint==1.37.1; extra == "dev"
Dynamic: license-file
